Metadata-Version: 1.0
Name: biopip
Version: 0.1
Summary: biostrand bioinformatics pipelines
Home-page: https://github.com/BioStrand/biopip
Author: UNKNOWN
Author-email: UNKNOWN
License: UNKNOWN
Platform: UNKNOWN
